odoo/addons/base_rest_base_structure/README.rst
odoo/addons/base_rest_base_structure/__init__.py
odoo/addons/base_rest_base_structure/__manifest__.py
odoo/addons/base_rest_base_structure/controllers/__init__.py
odoo/addons/base_rest_base_structure/controllers/main_controllers.py
odoo/addons/base_rest_base_structure/models/api_services_utils.py
odoo/addons/base_rest_base_structure/services/__init__.py
odoo/addons/base_rest_base_structure/services/abstract_services.py
odoo12_addon_base_rest_base_structure-12.0.1.0.3.dist-info/METADATA
odoo12_addon_base_rest_base_structure-12.0.1.0.3.dist-info/WHEEL
odoo12_addon_base_rest_base_structure-12.0.1.0.3.dist-info/top_level.txt
odoo12_addon_base_rest_base_structure-12.0.1.0.3.dist-info/RECORD
