Metadata-Version: 2.1
Name: odoo12-addon-base-rest-base-structure
Version: 12.0.1.0.3
Summary: Provide base controllers and services for simplifiying custom API implementation.
Home-page: https://gitlab.com/coopdevs/odoo-addons
Author: Coopdevs Treball SCCL
License: AGPL-3
Platform: UNKNOWN
Classifier: Programming Language :: Python
Classifier: Framework :: Odoo
Classifier: Framework :: Odoo :: 12.0
Classifier: License :: OSI Approved :: GNU Affero General Public License v3
Requires-Python: >=3.5
Requires-Dist: odoo12-addon-auth-api-key
Requires-Dist: odoo12-addon-base-rest
Requires-Dist: odoo (<12.1dev,>=12.0a)
